confetta/__init__.py
confetta/_docker_host.py
confetta/_docker_ports.py
confetta/_docker_service.py
confetta/_git_folder_name.py
confetta/py.typed
confetta-0.1.1.dist-info/LICENSE
confetta-0.1.1.dist-info/METADATA
confetta-0.1.1.dist-info/WHEEL
confetta-0.1.1.dist-info/top_level.txt
confetta-0.1.1.dist-info/RECORD
